unsiotools.libs/libWDutils-389b5de9.so
unsiotools.libs/libaec-91f0ca0f.so.0.0.8
unsiotools.libs/libcom_err-b4375b23.so.2.1
unsiotools.libs/libcrypto-401bea5d.so.1.1.1k
unsiotools.libs/libfalcON-d784e00a.so
unsiotools.libs/libgfortran-93980b03.so.5.0.0
unsiotools.libs/libgssapi_krb5-134fb67a.so.2.2
unsiotools.libs/libhdf5-b5e70f84.so.103.1.0
unsiotools.libs/libhdf5_cpp-165bc8b8.so.103.1.0
unsiotools.libs/libk5crypto-c7449546.so.3.1
unsiotools.libs/libkeyutils-2777d33d.so.1.6
unsiotools.libs/libkrb5-d5e439bf.so.3.3
unsiotools.libs/libkrb5support-de4617ba.so.0.1
unsiotools.libs/libpcre2-8-516f4c9d.so.0.7.1
unsiotools.libs/libpgplot-289e936d.so
unsiotools.libs/libquadmath-776d53b6.so.0.0.0
unsiotools.libs/libselinux-64a010fa.so.1
unsiotools.libs/libsqlite3-4576baee.so.0.8.6
unsiotools.libs/libsz-0deeef7d.so.2.0.1
unsiotools.libs/libtirpc-cff449a4.so.3.0.0
unsiotools.libs/libunsio-b656f282.so
unsiotools/__init__.py
unsiotools/_py_unstools.cpython-38-x86_64-linux-gnu.so
unsiotools/examples/test_cfalcon.py
unsiotools/general/__init__.py
unsiotools/general/ctools.py
unsiotools/libJCLprojects.so
unsiotools/libJCLutils.so
unsiotools/py_unstools.py
unsiotools/simulations/__init__.py
unsiotools/simulations/c2dpgplot.py
unsiotools/simulations/c2dplot.py
unsiotools/simulations/ccod.py
unsiotools/simulations/ccom.py
unsiotools/simulations/cfalcon.py
unsiotools/simulations/cinert.py
unsiotools/simulations/cmovie.py
unsiotools/simulations/corbits.py
unsiotools/simulations/cplotinert.py
unsiotools/simulations/cramses2gadget.py
unsiotools/simulations/crectify.py
unsiotools/simulations/creducesim.py
unsiotools/simulations/csnapshot.py
unsiotools/simulations/ctestunsio.py
unsiotools/simulations/ctree.py
unsiotools/simulations/cuns_analysis.py
unsiotools/uns_simu.py
unsiotools/version.py
unsiotools-1.0.2rc1.dist-info/METADATA
unsiotools-1.0.2rc1.dist-info/WHEEL
unsiotools-1.0.2rc1.dist-info/entry_points.txt
unsiotools-1.0.2rc1.dist-info/licenses/LICENSE
unsiotools-1.0.2rc1.dist-info/RECORD
