Metadata-Version: 2.2
Name: unsiotools
Version: 1.0.2rc1
Summary: A collection of unsio based programs
Keywords: astrophysics,computing
Author-Email: Jean-Charles Lambert <Jean-Charles.Lambert@lam.fr>
License: 
Classifier: Intended Audience :: Science/Research
Classifier: Programming Language :: C
Classifier: Programming Language :: C++
Classifier: Programming Language :: Python
Classifier: Programming Language :: Python :: 3.8
Classifier: Programming Language :: Python :: 3.9
Classifier: Programming Language :: Python :: 3.10
Classifier: Programming Language :: Python :: 3.11
Classifier: Programming Language :: Python :: 3.12
Classifier: Programming Language :: Python :: 3.13
Classifier: Topic :: Scientific/Engineering :: Astronomy
Requires-Python: >=3.8
Requires-Dist: numpy
Requires-Dist: unsio
Requires-Dist: matplotlib
Requires-Dist: scipy
